ffcuesplitter/__init__.py
ffcuesplitter/about.py
ffcuesplitter/cue_parser.py
ffcuesplitter/cuesplitter.py
ffcuesplitter/exceptions.py
ffcuesplitter/ffmpeg.py
ffcuesplitter/ffprobe.py
ffcuesplitter/main.py
ffcuesplitter/str_utils.py
ffcuesplitter/user_service.py
ffcuesplitter/utils.py
ffcuesplitter-1.0.31.data/data/share/man/man1/ffcuesplitter.1.gz
ffcuesplitter-1.0.31.dist-info/METADATA
ffcuesplitter-1.0.31.dist-info/WHEEL
ffcuesplitter-1.0.31.dist-info/entry_points.txt
ffcuesplitter-1.0.31.dist-info/licenses/AUTHORS
ffcuesplitter-1.0.31.dist-info/licenses/LICENSE
ffcuesplitter-1.0.31.dist-info/RECORD
