Metadata-Version: 2.4
Name: ffcuesplitter
Version: 1.0.31
Summary: FFmpeg-based audio splitter for CDDA images associated with .cue files .
Project-URL: Homepage, https://github.com/jeanslack/FFcuesplitter
Project-URL: Documentation, https://github.com/jeanslack/FFcuesplitter#readme
Project-URL: Wiki, https://github.com/jeanslack/FFcuesplitter/wiki
Project-URL: Tracker, https://github.com/jeanslack/Videomass/issues
Author-email: Gianluca Pernigotto <jeanlucperni@gmail.com>
Maintainer-email: Gianluca Pernigotto <jeanlucperni@gmail.com>
License: GNU General Public License v3 (GPLv3)
License-File: AUTHORS
License-File: LICENSE
Keywords: audio splitter,converter,ffcuesplitter,ffmpeg
Classifier: Development Status :: 5 - Production/Stable
Classifier: Environment :: Console
Classifier: Intended Audience :: Developers
Classifier: Intended Audience :: End Users/Desktop
Classifier: License :: OSI Approved :: GNU General Public License v3 (GPLv3)
Classifier: Natural Language :: English
Classifier: Operating System :: MacOS :: MacOS X
Classifier: Operating System :: Microsoft :: Windows
Classifier: Operating System :: POSIX :: Linux
Classifier: Programming Language :: Python :: 3 :: Only
Classifier: Programming Language :: Python :: 3.9
Classifier: Programming Language :: Python :: 3.10
Classifier: Programming Language :: Python :: 3.11
Classifier: Programming Language :: Python :: 3.12
Classifier: Topic :: Multimedia :: Sound/Audio :: Conversion
Classifier: Topic :: Utilities
Requires-Python: >=3.9
Requires-Dist: charset-normalizer>=3.0.1
Requires-Dist: tqdm>=4.38.0
